{
  "type": "FeatureCollection",
  "features": [
    {
      "type": "Feature",
      "properties": {
        "name": "Frankfurt UAS
      },
      "geometry": {
        "coordinates": [
          [
            [
              8.69298230074574,
              50.12943806766884
            ],
            [
              8.693707347493216,
              50.12962489671568
            ],
            [
              8.694005896154096,
              50.13024006037389
            ],
            [
              8.693529639956608,
              50.13037220560963
            ],
            [
              8.694005896154096,
              50.13133366513037
            ],
            [
              8.693430123737016,
              50.13144758085514
            ],
            [
              8.692520261151401,
              50.13140657122554
            ],
            [
              8.69192316382967,
              50.13146580734619
            ],
            [
              8.69188762232298,
              50.131684524694265
            ],
            [
              8.691631723470351,
              50.13167996809298
            ],
            [
              8.691631723470351,
              50.13148403383002
            ],
            [
              8.691183900479103,
              50.13144302423126
            ],
            [
              8.69136160801574,
              50.13071395883679
            ],
            [
              8.690935109927977,
              50.130700288754696
            ],
            [
              8.690928001627555,
              50.13011702827515
            ],
            [
              8.69298230074574,
              50.12943806766884
            ]
          ]
        ],
        "type": "Polygon"
      }
    }
  ]
}